icfs/__init__.py
icfs/eepromfs.py
icfs/config/eepromfs.yaml
icfs/config/filetype.yaml
icfs/lib/__init__.py
icfs/lib/eeprom_math.py
icfs-0.1.0.dist-info/LICENSE
icfs-0.1.0.dist-info/METADATA
icfs-0.1.0.dist-info/WHEEL
icfs-0.1.0.dist-info/top_level.txt
icfs-0.1.0.dist-info/RECORD
